{"nama": "Amelia Handayani", "tempat_lahir": "Kota Bitung", "tanggal_lahir": "13-11-1997", "jenis_kelamin": "Perempuan", "status_kawin": "Belum Kawin", "alamat": "Gang Raya Setiabudhi No. 799, Kota Bitung", "no_hp": "0874084924", "email": "owulandari@example.net", "nik": "7174669711530004", "sd_nama": "SD 82 Kota Bitung", "sd_tahun": "2005", "smp_nama": "MTS 9 Kota Bitung", "smp_tahun": "2012", "sma_nama": "SMK 36 Kota Bitung", "sma_tahun": "2016", "terakhir_jenjang": "S1", "terakhir_institusi": "UIN BATU BARA", "terakhir_jurusan": "Sistem Informasi", "terakhir_tahun": "2002", "kerja_perusahaan": "CV Wibisono Puspasari (Persero) Tbk", "kerja_posisi": "Restaurant manager", "kerja_periode": "11", "kerja_gaji": "3.302.841", "kerja_alasan": "Reprehenderit provident optio quibusdam laboriosam ducimus repellendus. Consectetur nam eum cum. Excepturi praesentium sed nemo modi.", "applied_posisi": "Product manager", "expected_salary": "9.818.626", "start_date": "21-09-2025", "application_place": "Kota Bitung", "application_date": "22-08-2025"}