{"nama": "dr. Jayadi Putra, S.Gz", "tempat_lahir": "Pulau Taliabu", "tanggal_lahir": "16-08-1999", "jenis_kelamin": "Perempuan", "status_kawin": "Pernah Kawin", "alamat": "Jl. Tubagus Ismail No. 03, Pulau Taliabu", "no_hp": "0888073032", "email": "osihotang@example.org", "nik": "1771829908560005", "sd_nama": "SDN 77 Pulau Taliabu", "sd_tahun": "2006", "smp_nama": "SMPN 29 Pulau Taliabu", "smp_tahun": "2013", "sma_nama": "MAN 4 Pulau Taliabu", "sma_tahun": "2017", "terakhir_jenjang": "S1", "terakhir_institusi": "Universitas Negeri TAKALAR", "terakhir_jurusan": "Teknik Informatika", "terakhir_tahun": "2004", "kerja_perusahaan": "CV Usada", "kerja_posisi": "Web designer", "kerja_periode": "19", "kerja_gaji": "1.213.266", "kerja_alasan": "Hic quos distinctio non quia. Officiis velit magni illo fugiat quasi hic.", "applied_posisi": "Research scientist (life sciences)", "expected_salary": "7.693.277", "start_date": "03-02-2025", "application_place": "Pulau Taliabu", "application_date": "04-01-2025"}