{"nik": "1409330011050005", "nama": "Cindy Saptono", "tempat_lahir": "Batu Bara", "tanggal_lahir": "05-11-2000", "status_kawin": "Kawin", "alamat": "Jalan Ciumbuleuit No. 753, Batu Bara", "no_hp": "0810775463", "email": "apertiwi@example.org", "sd_nama": "SDIT 3 Batu Bara", "sd_tahun": "2007", "smp_nama": "SMP 12 Batu Bara", "smp_tahun": "2013", "sma_nama": "SMK 80 Batu Bara", "sma_tahun": "2016", "terakhir_jenjang": "D1", "terakhir_institusi": "Universitas Negeri JOMBANG", "terakhir_jurusan": "Sistem Informasi", "terakhir_tahun": "2019", "kerja_perusahaan": "CV Yulianti Sudiati Tbk", "kerja_posisi": "Veterinary surgeon", "kerja_periode": "35", "kerja_gaji": "3.960.761", "kerja_alasan": "Cupiditate fugit at eligendi necessitatibus veniam. Totam hic laboriosam delectus nam aliquid. Minima eaque magni laborum.\nRerum est vitae vitae. Deserunt porro minus.", "applied_posisi": "Psychologist, clinical", "expected_salary": "6.048.454", "start_date": "22-10-2025", "application_place": "Batu Bara", "application_date": "22-09-2025"}