{"nama_pelanggan": "Vera Sirait", "alamat_pelanggan": "Gang Dipatiukur No. 17", "telp_pelanggan": "0856581002", "nomor_invoice": "8005/INV/01/2023", "tanggal_invoice": "09-01-2023", "tanggal_jatuh_tempo": "22-02-2023", "item_description_1": "Telur Bebek", "item_qty_1": "42", "item_harga_1": "39,000", "item_jumlah_1": "1,638,000", "item_description_2": "Jagung", "item_qty_2": "71", "item_harga_2": "87,000", "item_jumlah_2": "6,177,000", "item_description_3": "Beras", "item_qty_3": "13", "item_harga_3": "18,000", "item_jumlah_3": "234,000", "subtotal": "8,049,000", "diskon": "643,920", "ppn": "885,390", "total_akhir": "8,290,470", "nama_direktur": "Titin Andriani"}