{"nama_pelanggan": "Wage Marbun", "alamat_pelanggan": "Gang Jend. A. Yani No. 0", "telp_pelanggan": "0820376844", "nomor_invoice": "2203/INV/04/2024", "tanggal_invoice": "04-04-2024", "tanggal_jatuh_tempo": "19-04-2024", "item_description_1": "Daging Ayam", "item_qty_1": "35", "item_harga_1": "50,000", "item_jumlah_1": "1,750,000", "item_description_2": "Daging Sapi", "item_qty_2": "18", "item_harga_2": "57,000", "item_jumlah_2": "1,026,000", "item_description_3": "Telur Ayam", "item_qty_3": "43", "item_harga_3": "57,000", "item_jumlah_3": "2,451,000", "subtotal": "5,227,000", "diskon": "365,890", "ppn": "574,970", "total_akhir": "5,436,080", "nama_direktur": "Dono Hakim"}